datasette_leaflet_freedraw/__init__.py
datasette_leaflet_freedraw/static/datasette-leaflet-freedraw.js
datasette_leaflet_freedraw/static/leaflet-freedraw.esm.js
datasette_leaflet_freedraw/static/leaflet-freedraw.esm.js.map
datasette_leaflet_freedraw-0.3.1.dist-info/METADATA
datasette_leaflet_freedraw-0.3.1.dist-info/WHEEL
datasette_leaflet_freedraw-0.3.1.dist-info/entry_points.txt
datasette_leaflet_freedraw-0.3.1.dist-info/top_level.txt
datasette_leaflet_freedraw-0.3.1.dist-info/RECORD
