Metadata-Version: 2.1
Name: datasette-leaflet-freedraw
Version: 0.3.1
Summary: Draw polygons on maps in Datasette
Home-page: https://github.com/simonw/datasette-leaflet-freedraw
Author: Simon Willison
License: Apache License, Version 2.0
Project-URL: Issues, https://github.com/simonw/datasette-leaflet-freedraw/issues
Project-URL: CI, https://github.com/simonw/datasette-leaflet-freedraw/actions
Project-URL: Changelog, https://github.com/simonw/datasette-leaflet-freedraw/releases
Platform: UNKNOWN
Requires-Python: >=3.6
Requires-Dist: datasette (>=0.60)
Requires-Dist: datasette-leaflet (>=0.2)
Provides-Extra: test
Requires-Dist: pytest ; extra == 'test'
Requires-Dist: pytest-asyncio ; extra == 'test'
